{
  "resources": [
    {
      "path": "data.csv",
      "name": "data",
      "profile": "tabular-data-resource",
      "scheme": "file",
      "format": "csv",
      "hashing": "md5",
      "encoding": "utf-8",
      "schema": {
        "fields": [
          {
            "name": "UNIT_MEASURE",
            "type": "string",
            "title": "Unit of measure"
          },
          {
            "name": "Unnamed: 4",
            "type": "string",
            "constraints": {
              "enum": [
                "",
                "0",
                "10",
                "1016",
                "1018",
                "1038",
                "1044",
                "1062",
                "1067",
                "1075",
                "1091",
                "1104",
                "1134",
                "122",
                "12288",
                "1245",
                "1250",
                "1255",
                "1279",
                "1285",
                "13",
                "13053",
                "1330",
                "1336",
                "13394",
                "1352",
                "1363",
                "1452",
                "1466",
                "158",
                "16",
                "1629",
                "174",
                "1829",
                "1860",
                "1896",
                "1919",
                "193",
                "1950",
                "1999",
                "2247",
                "235",
                "245",
                "247",
                "251",
                "268",
                "269",
                "272",
                "286",
                "299",
                "314",
                "3174",
                "327",
                "3286",
                "332",
                "339",
                "356",
                "361",
                "363",
                "373",
                "381",
                "384",
                "39",
                "397",
                "430",
                "434",
                "46",
                "467",
                "468",
                "481",
                "485",
                "486",
                "4977",
                "500",
                "507",
                "514",
                "5302",
                "5571",
                "585",
                "6",
                "604",
                "610",
                "612",
                "616",
                "625",
                "651",
                "662",
                "674",
                "678",
                "731",
                "7311",
                "738",
                "740",
                "747",
                "749",
                "772",
                "7751",
                "777",
                "778",
                "7823",
                "792",
                "85",
                "887",
                "899",
                "990"
              ]
            },
            "title": "Unnamed: 4"
          },
          {
            "name": "Value",
            "type": "string",
            "title": "Value"
          },
          {
            "name": "Year",
            "type": "integer",
            "title": "Year"
          },
          {
            "name": "type_of_education",
            "type": "string",
            "constraints": {
              "enum": [
                "",
                "agriculture_forestry_fisheries_and_veterinary_medicine",
                "arts_and_humanities",
                "business_administration_and_the_law_of_everything",
                "education",
                "engineering_manufacturing_and_construction",
                "health_and_social_protection",
                "information and communication technologies",
                "natural_sciences_mathematics_and_statistics_of_all",
                "services",
                "social_sciences_journalism_and_information",
                "Total",
                "Unknown"
              ]
            },
            "title": "Type of education"
          }
        ]
      }
    }
  ],
  "profile": "data-package",
  "name": "5-4-3",
  "title": "Graduated students by type of education"
}